{
	"pages": [ //pages数组中第一项表示应用启动页，参考：https://uniapp.dcloud.io/collocation/pages
		{
			"path": "pages/index/index",
			"style": {
				"navigationBarTitleText": "小朋友识数字"
			}
		},
		{
			"path" : "pages/num-Huarongdao/num-Huarongdao",
			"style" : 
			{
				"navigationBarTitleText" : "基础数字训练"
			}
		},
		{
			"path" : "pages/know-num/know-num",
			"style" : 
			{
				"navigationBarTitleText" : "认识数字"
			}
		},
		{
			"path" : "pages/num-memory/num-memory",
			"style" : 
			{
				"navigationBarTitleText" : "综合训练"
			}
		},
		{
			"path" : "pages/my/my",
			"style" : 
			{
				"navigationBarTitleText" : "我的"
			}
		},
		{
			"path" : "pages/game-score-rank/game-score-rank",
			"style" : 
			{
				"navigationBarTitleText" : "游戏排行"
			}
		}
	],
	"globalStyle": {
		"navigationBarTextStyle": "black",
		"navigationBarTitleText": "uni-app",
		"navigationBarBackgroundColor": "#F8F8F8",
		"backgroundColor": "#F8F8F8"
	},
	"tabBar": {
		"color": "#9799a5",
		"selectedColor": "#28B389",
		"list": [
			{
				"text": "玩玩",
				"pagePath": "pages/index/index",
				"iconPath": "static/images/tabBar/home.png",
				"selectedIconPath": "static/images/tabBar/home-h.png"
			},{
				"text": "我的",
				"pagePath": "pages/my/my",
				"iconPath": "static/images/tabBar/user.png",
				"selectedIconPath": "static/images/tabBar/user-h.png"
			}
		]
	},
	"uniIdRouter": {}
}
